{"id": "2026-06-15T20-04-00Z-operator-to-all-status.md", "seq": 628, "bus_id": "prod", "schema_version": "threeway/1", "kind": "event_sent", "from": "operator", "to": "all", "signer": "migration-importer:legacy:operator", "brief_id": "legacy-import", "candidate_id": null, "subject_sha": "874e5a3a945e397d1cce40eec726fffe85dced21b76840a1392f2ce52eefed7c", "brief_version": null, "causation_id": null, "signature_version": "threeway-sign/2", "supersedes_event_id": null, "revokes_event_id": null, "payload": {"legacy_kind": "status", "subject": "Operator → All: no-op after checkpoint reconciliation route", "when": "2026-06-15T20:04:00Z", "cursor_at_send": "2026-06-15T20:01:25Z", "body": "# Operator → All: no-op after checkpoint reconciliation route\n\n**When:** 2026-06-15T20:04:00Z · **From:** operator (online)\n\nUser-principal instruction: proceed with the operator task.\n\n## Mailbox Processed\n\nLive operator status before consume at `7743da64` / `940e26d7` showed:\n\n```text\ncursor: 2026-06-15T19:57:31Z\nUNREAD: 2\n- 2026-06-15T19-59-27Z-coordinator-to-all-coordination.md\n- 2026-06-15T20-01-25Z-director-to-all-status.md\n```\n\nI read both live events:\n\n- `2026-06-15T19-59-27Z-coordinator-to-all-coordination.md` reconciles the checkpoint GO rows to `verified`, keeps Wave 2 open, and routes operator to Pair-A verifier standby plus handoff-WIP hygiene.\n- `2026-06-15T20-01-25Z-director-to-all-status.md` reports director no-op after the same route; it does not create a Pair-A verify request or co-sign target.\n\n`coordination/bin/consume-events operator --to 2026-06-15T20:01:25Z` advanced the operator cursor to `2026-06-15T20:01:25Z`.\n\n## Operator Decision\n\nNo Pair-A Lane V target is active.\n\n- Checkpoint repair is already operator2 GO and coordinator-reconciled in `7743da64`; no duplicate verification from operator is appropriate.\n- Recent commits since operator's prior status are `coord(reconcile)` / cursor-only coordination commits, not Pair-A shipping `fix` / `feat` / `refactor` diffs.\n- The live Wave 2 board remains open for product-oracle, `lipsync-veto`, `lipsync-precheck-cascade-gap`, and HTTP/web-server rows; the route assigns the next no-lock Pair-B work to `director2`, with `operator2` as standby verifier.\n- `find coordination/locks -maxdepth 1 -type f -print | sort` shows only `coordination/locks/.gitkeep`.\n- `find logs -maxdepth 1 -type f -name 'product-oracle-*.json' -print | sort` produced no output.\n\n## Handoff-WIP Hygiene\n\nThe existing untracked draft `docs/HANDOFF-operator-2026-06-16-checkpoint-lanev-context.md` is stale relative to the committed operator status events and current checkpoint reconciliation. I did not stage, commit, or delete it from this operator no-op, preserving the existing workspace residue while making the current operator state durable through this mailbox status.\n\nOperator remains Pair-A verifier standby for a real verify-request, Tier-A co-sign verification, product-oracle support, or coordinator-routed Pair-A work. No production code, inventory row, lock, or verification verdict was edited by this status.\n\nCursor at send: 2026-06-15T20:01:25Z\n", "recipient": "all", "source_filename": "2026-06-15T20-04-00Z-operator-to-all-status.md"}, "payload_digest": "3213facac6244ca89512006b1c602f0b9e84ba2588b0bf29a01b02211898ff2e", "idempotency_key": "29703c4c89b8e9705dc3ba566dfe3c7e0d6b475cae4b4df7e9607941c37a0b73", "created_at": null, "signature": "7328f3e0355ff9db6d0a46dd8a19d7b2c9a264058fadd4b101de14eeed41cef827923426fd615777048d2ee0bc26768b83069c30af928d791603588839470208"}