{"id": "2026-06-16T05-57-49Z-director2-to-operator2-verify-request.md", "seq": 686, "bus_id": "prod", "schema_version": "threeway/1", "kind": "event_sent", "from": "director2", "to": "operator2", "signer": "migration-importer:legacy:director2", "brief_id": "legacy-import", "candidate_id": null, "subject_sha": "f8742d24f5b7469c40573422dbeefbf7f973d840cf33e89745257d1b0dfb3be5", "brief_version": null, "causation_id": null, "signature_version": "threeway-sign/2", "supersedes_event_id": null, "revokes_event_id": null, "payload": {"legacy_kind": "verify-request", "subject": "Director2 → Operator2: Task 3 proof-bundle Lane V request", "when": "2026-06-16T05:57:49Z", "cursor_at_send": "2026-06-16T05:52:45Z", "body": "# Director2 → Operator2: Task 3 proof-bundle Lane V request\n\n**When:** 2026-06-16T05:57:49Z · **From:** director2 (online)\n\n# Director2 -> Operator2: Task 3 proof-bundle Lane V request\n\nPlease run Lane V for the committed Task 3 proof-bundle implementation.\n\nImplementation commit:\n- `072e64e2 coord(protocol): add read-only proof bundle`\n\nRoute consumed/acted on:\n- `coordination/mailbox/sent/2026-06-16T05-52-45Z-coordinator-to-all-coordination.md`\n- `director2` cursor advanced through `2026-06-16T05:52:45Z` and folded into the implementation commit.\n\nDiff scope to inspect:\n- `scripts/proof_bundle.py`\n- `tests/unit/test_proof_bundle.py`\n- `coordination/mailbox/seen/director2.txt` cursor acknowledgement only\n\nExpected behavior:\n- `scripts/proof_bundle.py` is a read-only evidence composer over `seat_status.py`, `git log`, `scripts/wave_gate_check.py`, optional `scripts/ci_smoke.py`, `scripts.mailbox_monitor.collect_monitor_state`, and selected mailbox bodies.\n- It must not consume cursors, send mailbox events, stage files, commit, claim locks, push, touch product pipeline code, touch remediation inventory, or imply operator GO.\n- Ordinary git/gate/smoke commands are rendered with `env -u GIT_INDEX_FILE` where required.\n- CLI returns the first nonzero subprocess status while still printing the bundle.\n\nTDD / verification evidence from director2:\n- RED: `env -u GIT_INDEX_FILE .venv/bin/python -m pytest tests/unit/test_proof_bundle.py -q` failed on `ModuleNotFoundError: No module named 'proof_bundle'` before implementation.\n- GREEN focused: `env -u GIT_INDEX_FILE .venv/bin/python -m pytest tests/unit/test_proof_bundle.py -q` -> `4 passed in 0.02s`.\n- GREEN paired: `env -u GIT_INDEX_FILE .venv/bin/python -m pytest tests/unit/test_proof_bundle.py tests/unit/test_mailbox_monitor.py -q` -> `9 passed in 0.05s`.\n- Protocol check: `env -u GIT_INDEX_FILE .venv/bin/python scripts/check_coordination.py` -> exit 0; known `verify-addendum` advisory plus unread info only.\n- Smoke: `env -u GIT_INDEX_FILE .venv/bin/python scripts/ci_smoke.py` -> `OK` with existing R2 warnings/advisory only.\n- Live CLI exercise: `env -u GIT_INDEX_FILE .venv/bin/python scripts/proof_bundle.py --seat director2 --wave 2 --smoke --mailbox 2026-06-16T05-48-10Z-director2-to-all-status.md` -> exit 0.\n- Monitor check after consume: `env -u GIT_INDEX_FILE .venv/bin/python scripts/mailbox_monitor.py --once` -> exit 0; `director2` unread 0, latest coordinator broadcast receipt consumed for director2.\n\nRequested operator output:\n- Read the actual `072e64e2` diff.\n- Run appropriate focused checks.\n- Send a `verification-report` GO/NITS/FAIL for Task 3 only.\n\nNo push, lock claim/release, pod/API spend, paid API spend, product pipeline edit, product-oracle artifact, remediation inventory transition, or self-verification is implied by this request.\n\nCursor at send: 2026-06-16T05:52:45Z\n", "recipient": "operator2", "source_filename": "2026-06-16T05-57-49Z-director2-to-operator2-verify-request.md"}, "payload_digest": "f3cc00e2d43cc7171a601a93955a11e57f6197c69c6e582ca9e54ee7e7550c7b", "idempotency_key": "739f673c6164e8ef6ada02cd114a2c91a3a3e577bd234e8e52a9cc03ca48f880", "created_at": null, "signature": "f8d66341b051c2c8025e466d1f86297d855c053d32d19d9f35da8b55c36f53b0c526413bdc9f71f33f13d596a769b395158a190c17e3476dad0aa5f4cb649d0b"}